dsc_it100/__init__.py
dsc_it100/driver.py
dsc_it100/exceptions.py
dsc_it100/protocol.py
dsc_it100/state.py
dsc_it100-0.1.1.dist-info/DESCRIPTION.rst
dsc_it100-0.1.1.dist-info/METADATA
dsc_it100-0.1.1.dist-info/RECORD
dsc_it100-0.1.1.dist-info/WHEEL
dsc_it100-0.1.1.dist-info/metadata.json
dsc_it100-0.1.1.dist-info/top_level.txt
