Metadata-Version: 2.0
Name: dsc-it100
Version: 0.1.1
Summary: A Python driver for the DSC IT-100 integration module.
Home-page: https://github.com/kostko/dsc-it100
Author: Jernej Kos
Author-email: jernej@kos.mx
License: AGPLv3
Platform: UNKNOWN
Classifier: Development Status :: 4 - Beta
Classifier: Intended Audience :: Developers
Classifier: License :: OSI Approved :: GNU Affero General Public License v3
Classifier: Operating System :: OS Independent
Classifier: Programming Language :: Python
Requires-Dist: pyserial (>=3.2.1)
Requires-Dist: pyserial-asyncio (>=0.2)
